pronotepy/__init__.py
pronotepy/clients.py
pronotepy/create_login.py
pronotepy/dataClasses.py
pronotepy/exceptions.py
pronotepy/pronoteAPI.py
pronotepy/py.typed
pronotepy/test_pronotepy.py
pronotepy/ent/__init__.py
pronotepy/ent/complex_ent.py
pronotepy/ent/ent.py
pronotepy/ent/generic_func.py
pronotepy/ent/test_ent.py
pronotepy-2.14.5.dist-info/LICENSE
pronotepy-2.14.5.dist-info/METADATA
pronotepy-2.14.5.dist-info/WHEEL
pronotepy-2.14.5.dist-info/top_level.txt
pronotepy-2.14.5.dist-info/RECORD
