Metadata-Version: 2.1
Name: pronotepy
Version: 2.14.5
Summary: A wrapper for the pronote "API"
Home-page: https://www.github.com/bain3/pronotepy
Author: bain
License: MIT
Classifier: Programming Language :: Python :: 3
Classifier: License :: OSI Approved :: MIT License
Classifier: Operating System :: OS Independent
Requires-Python: >=3.8
License-File: LICENSE
Requires-Dist: beautifulsoup4>=4.8.2
Requires-Dist: pycryptodome>=3.9.4
Requires-Dist: requests>=2.22.0
Requires-Dist: autoslot>=2022.12.1
